jx/__init__.py
jx/attrs.py
jx/catalog.py
jx/component.py
jx/exceptions.py
jx/meta.py
jx/parser.py
jx/utils.py
jx-0.2.0.dist-info/licenses/LICENSE
jx-0.2.0.dist-info/METADATA
jx-0.2.0.dist-info/WHEEL
jx-0.2.0.dist-info/top_level.txt
jx-0.2.0.dist-info/RECORD
