Metadata-Version: 2.4
Name: jx
Version: 0.2.0
Summary: Replace your HTML templates with Python server-Side components
Author-email: Juan Pablo Scaletti <juanpablo@jpscaletti.com>
Project-URL: homepage, https://jx.scaletti.dev/
Project-URL: repository, https://github.com/jpsca/jx
Project-URL: documentation, https://jx.scaletti.dev/
Classifier: Development Status :: 4 - Beta
Classifier: Environment :: Web Environment
Classifier: Intended Audience :: Developers
Classifier: Programming Language :: Python :: 3 :: Only
Classifier: Programming Language :: Python :: 3.11
Classifier: Programming Language :: Python :: 3.12
Classifier: Programming Language :: Python :: 3.13
Classifier: Topic :: Internet :: WWW/HTTP :: Dynamic Content
Classifier: Topic :: Software Development :: Libraries
Classifier: Topic :: Software Development :: Libraries :: Python Modules
Classifier: Topic :: Software Development :: User Interfaces
Classifier: Topic :: Text Processing :: Markup :: HTML
Classifier: Typing :: Typed
Requires-Python: <4,>=3.11
License-File: LICENSE
Requires-Dist: jinja2>=3.0
Requires-Dist: markupsafe>=2.0
Requires-Dist: ty>=0.0.1a15
Dynamic: license-file
